CHANGELOG.md
LICENSE
django_version_viewer/__init__.py
django_version_viewer/cms_toolbars.py
django_version_viewer/mixins.py
django_version_viewer/pip_viewer.py
django_version_viewer/templates/toolbar.html
django_version_viewer/templates/version_viewer.html
django_version_viewer/templatetags/__init__.py
django_version_viewer/templatetags/pip_version_viewer_tags.py
django_version_viewer/tests/__init__.py
django_version_viewer/tests/test_get_accessor_class.py
django_version_viewer/tests/test_superuser_accessor.py
django_version_viewer/tests/test_views.py
django_version_viewer/urls.py
django_version_viewer/utils.py
django_version_viewer/views.py
django_version_viewer-2.1.8.dist-info/LICENSE
django_version_viewer-2.1.8.dist-info/METADATA
django_version_viewer-2.1.8.dist-info/WHEEL
django_version_viewer-2.1.8.dist-info/RECORD
